render_template/__init__.py
render_template/cli.py
render_template/render.py
render_template-0.2.0.dist-info/METADATA
render_template-0.2.0.dist-info/WHEEL
render_template-0.2.0.dist-info/entry_points.txt
render_template-0.2.0.dist-info/top_level.txt
render_template-0.2.0.dist-info/RECORD
