Metadata-Version: 2.1
Name: render-template
Version: 0.2.0
Requires-Python: >=3.8
Requires-Dist: pyyaml
Requires-Dist: jinja2
Requires-Dist: mako
Requires-Dist: pystache
Provides-Extra: test
Requires-Dist: cram; extra == "test"
